deluge_utilities/__init__.py
deluge_utilities/deluge.py
deluge_utilities-0.0.4.dist-info/METADATA
deluge_utilities-0.0.4.dist-info/WHEEL
deluge_utilities-0.0.4.dist-info/entry_points.txt
deluge_utilities-0.0.4.dist-info/top_level.txt
deluge_utilities-0.0.4.dist-info/RECORD
