Metadata-Version: 2.1
Name: deluge-utilities
Version: 0.0.4
Summary: Is a set of utilities to help you work with Deluge.
Home-page: https://github.com/GitBib/deluge-utilities
Download-URL: https://github.com/GitBib/deluge-utilities/archive/0.0.4.zip
Author: Ivan Vyalov
Author-email: job@bnff.website
License: Apache License, Version 2.0, see LICENSE file
Classifier: License :: OSI Approved :: Apache Software License
Classifier: Operating System :: OS Independent
Classifier: Programming Language :: Python
Classifier: Programming Language :: Python :: 3.8
Classifier: Programming Language :: Python :: 3.9
Classifier: Programming Language :: Python :: 3.10
Classifier: Programming Language :: Python :: Implementation :: PyPy
Classifier: Programming Language :: Python :: Implementation :: CPython
Requires-Dist: setuptools
Requires-Dist: deluge-client
